<?xml version="1.0" encoding="Windows-1252" ?>
<NotepadPlus>
	<AutoComplete language="mcfunction">
		<Environment ignoreCase="yes"/>
		<KeyWord name="actionbar"/>
		<KeyWord name="add"/>
		<KeyWord name="advancement"/>
		<KeyWord name="align"/>
		<KeyWord name="all"/>
		<KeyWord name="ambient"/>
		<KeyWord name="amount"/>
		<KeyWord name="anchored"/>
		<KeyWord name="append"/>
		<KeyWord name="as"/>
		<KeyWord name="at"/>
		<KeyWord name="attacker"/>
		<KeyWord name="attribute"/>
		<KeyWord name="available"/>
		<KeyWord name="ban"/>
		<KeyWord name="ban-ip"/>
		<KeyWord name="banlist"/>
		<KeyWord name="base"/>
		<KeyWord name="biome"/>
		<KeyWord name="block"/>
		<KeyWord name="blocks"/>
		<KeyWord name="bossbar"/>
		<KeyWord name="buffer"/>
		<KeyWord name="by"/>
		<KeyWord name="clear"/>
		<KeyWord name="clone"/>
		<KeyWord name="color"/>
		<KeyWord name="controller"/>
		<KeyWord name="damage"/>
		<KeyWord name="damage"/>
		<KeyWord name="data"/>
		<KeyWord name="data"/>
		<KeyWord name="datapack"/>
		<KeyWord name="debug"/>
		<KeyWord name="defaultgamemode"/>
		<KeyWord name="deop"/>
		<KeyWord name="destroy"/>
		<KeyWord name="difficulty"/>
		<KeyWord name="dimension"/>
		<KeyWord name="disable"/>
		<KeyWord name="dismount"/>
		<KeyWord name="displayname"/>
		<KeyWord name="distance"/>
		<KeyWord name="effect"/>
		<KeyWord name="empty"/>
		<KeyWord name="enable"/>
		<KeyWord name="enabled"/>
		<KeyWord name="enchant"/>
		<KeyWord name="entity"/>
		<KeyWord name="everything"/>
		<KeyWord name="execute"/>
		<KeyWord name="experience"/>
		<KeyWord name="eyes"/>
		<KeyWord name="facing"/>
		<KeyWord name="feature"/>
		<KeyWord name="feet"/>
		<KeyWord name="fill"/>
		<KeyWord name="fillbiome"/>
		<KeyWord name="filtered"/>
		<KeyWord name="fish"/>
		<KeyWord name="force"/>
		<KeyWord name="forceload"/>
		<KeyWord name="from"/>
		<KeyWord name="function"/>
		<KeyWord name="gamemode"/>
		<KeyWord name="gamerule"/>
		<KeyWord name="get"/>
		<KeyWord name="give"/>
		<KeyWord name="grant"/>
		<KeyWord name="help"/>
		<KeyWord name="hollow"/>
		<KeyWord name="hostile"/>
		<KeyWord name="if"/>
		<KeyWord name="in"/>
		<KeyWord name="insert"/>
		<KeyWord name="item"/>
		<KeyWord name="jfr"/>
		<KeyWord name="jigsaw"/>
		<KeyWord name="join"/>
		<KeyWord name="keep"/>
		<KeyWord name="kick"/>
		<KeyWord name="kill"/>
		<KeyWord name="leasher"/>
		<KeyWord name="leave"/>
		<KeyWord name="levels"/>
		<KeyWord name="list"/>
		<KeyWord name="list"/>
		<KeyWord name="loaded"/>
		<KeyWord name="locate"/>
		<KeyWord name="loot"/>
		<KeyWord name="loot"/>
		<KeyWord name="masked"/>
		<KeyWord name="master"/>
		<KeyWord name="max"/>
		<KeyWord name="me"/>
		<KeyWord name="merge"/>
		<KeyWord name="mine"/>
		<KeyWord name="modifier"/>
		<KeyWord name="modify"/>
		<KeyWord name="mount"/>
		<KeyWord name="move"/>
		<KeyWord name="msg"/>
		<KeyWord name="multiply"/>
		<KeyWord name="multiply_base"/>
		<KeyWord name="music"/>
		<KeyWord name="name"/>
		<KeyWord name="neutral"/>
		<KeyWord name="normal"/>
		<KeyWord name="objectives"/>
		<KeyWord name="off"/>
		<KeyWord name="on"/>
		<KeyWord name="only"/>
		<KeyWord name="op"/>
		<KeyWord name="operation"/>
		<KeyWord name="origin"/>
		<KeyWord name="outline"/>
		<KeyWord name="over"/>
		<KeyWord name="owner"/>
		<KeyWord name="pardon"/>
		<KeyWord name="pardon-ip"/>
		<KeyWord name="particle"/>
		<KeyWord name="passengers"/>
		<KeyWord name="perf"/>
		<KeyWord name="place"/>
		<KeyWord name="player"/>
		<KeyWord name="players"/>
		<KeyWord name="playsound"/>
		<KeyWord name="poi"/>
		<KeyWord name="points"/>
		<KeyWord name="positioned"/>
		<KeyWord name="predicate"/>
		<KeyWord name="prepend"/>
		<KeyWord name="publish"/>
		<KeyWord name="query"/>
		<KeyWord name="recipe"/>
		<KeyWord name="record"/>
		<KeyWord name="reload"/>
		<KeyWord name="remove"/>
		<KeyWord name="rendertype"/>
		<KeyWord name="replace"/>
		<KeyWord name="reset"/>
		<KeyWord name="result"/>
		<KeyWord name="revoke"/>
		<KeyWord name="ride"/>
		<KeyWord name="rotated"/>
		<KeyWord name="run"/>
		<KeyWord name="save-all"/>
		<KeyWord name="save-off"/>
		<KeyWord name="save-on"/>
		<KeyWord name="say"/>
		<KeyWord name="schedule"/>
		<KeyWord name="score"/>
		<KeyWord name="scoreboard"/>
		<KeyWord name="seed"/>
		<KeyWord name="set"/>
		<KeyWord name="setblock"/>
		<KeyWord name="setdisplay"/>
		<KeyWord name="setidletimeout"/>
		<KeyWord name="setworldspawn"/>
		<KeyWord name="spawn"/>
		<KeyWord name="spawnpoint"/>
		<KeyWord name="spectate"/>
		<KeyWord name="spreadplayers"/>
		<KeyWord name="start"/>
		<KeyWord name="stop"/>
		<KeyWord name="stop"/>
		<KeyWord name="stopsound"/>
		<KeyWord name="storage"/>
		<KeyWord name="store"/>
		<KeyWord name="string"/>
		<KeyWord name="structure"/>
		<KeyWord name="style"/>
		<KeyWord name="subtitle"/>
		<KeyWord name="success"/>
		<KeyWord name="summon"/>
		<KeyWord name="tag"/>
		<KeyWord name="take"/>
		<KeyWord name="team"/>
		<KeyWord name="teammsg"/>
		<KeyWord name="teleport"/>
		<KeyWord name="tell"/>
		<KeyWord name="tellraw"/>
		<KeyWord name="template"/>
		<KeyWord name="through"/>
		<KeyWord name="time"/>
		<KeyWord name="time"/>
		<KeyWord name="times"/>
		<KeyWord name="title"/>
		<KeyWord name="tm"/>
		<KeyWord name="to"/>
		<KeyWord name="tp"/>
		<KeyWord name="trigger"/>
		<KeyWord name="under"/>
		<KeyWord name="unless"/>
		<KeyWord name="until"/>
		<KeyWord name="uuids"/>
		<KeyWord name="value"/>
		<KeyWord name="vehicle"/>
		<KeyWord name="visible"/>
		<KeyWord name="voice"/>
		<KeyWord name="warning"/>
		<KeyWord name="weather"/>
		<KeyWord name="weather"/>
		<KeyWord name="whitelist"/>
		<KeyWord name="with"/>
		<KeyWord name="worldborder"/>
		<KeyWord name="xp"/>
	</AutoComplete>
</NotepadPlus>
